lsyiot_adapter_plugin/__init__.py
lsyiot_adapter_plugin/negotiation.py
lsyiot_adapter_plugin/plugin_factory.py
lsyiot_adapter_plugin-1.0.2.dist-info/METADATA
lsyiot_adapter_plugin-1.0.2.dist-info/WHEEL
lsyiot_adapter_plugin-1.0.2.dist-info/top_level.txt
lsyiot_adapter_plugin-1.0.2.dist-info/RECORD
