Metadata-Version: 2.4
Name: lsyiot_adapter_plugin
Version: 1.0.2
Summary: 为lsyiot_adapter_hub提供适配器插件
Home-page: https://github.com/9kl/lsyiot_adapter_plugin
Author: fhp
Author-email: chinafengheping@outlook.com
Classifier: Programming Language :: Python :: 3
Classifier: License :: OSI Approved :: MIT License
Classifier: Operating System :: OS Independent
Requires-Python: >=3.8
Requires-Dist: pyyaml
Dynamic: author
Dynamic: author-email
Dynamic: classifier
Dynamic: description
Dynamic: description-content-type
Dynamic: home-page
Dynamic: requires-dist
Dynamic: requires-python
Dynamic: summary
